Metadata-Version: 2.1
Name: appchance-django
Version: 0.2.4
Summary: Common extensions for Django projects.
Home-page: https://bitbucket.org/appchance/appchance-django/
Author-email: backend@appchance.com
License: UNKNOWN
Platform: UNKNOWN
Classifier: Programming Language :: Python :: 3.8
Classifier: Operating System :: POSIX :: Linux
Requires-Python: >=3.8
Requires-Dist: django
Requires-Dist: swapper
